README.md
setup.py
romana/__init__.py
romana/romana.py
romana.egg-info/PKG-INFO
romana.egg-info/SOURCES.txt
romana.egg-info/dependency_links.txt
romana.egg-info/top_level.txt