Metadata-Version: 2.1
Name: romana
Version: 0.1
Summary: Roman numbers implemented to Python AST.
Home-page: https://github.com/abstractequalsmagic/romana
License: UNKNOWN
Platform: UNKNOWN
